LICENSE
MANIFEST.in
README.rst
helga_wiki_whois.py
setup.py
helga_wiki_whois.egg-info/PKG-INFO
helga_wiki_whois.egg-info/SOURCES.txt
helga_wiki_whois.egg-info/dependency_links.txt
helga_wiki_whois.egg-info/entry_points.txt
helga_wiki_whois.egg-info/top_level.txt
helga_wiki_whois.egg-info/zip-safe